genesys_notifications/__init__.py
genesys_notifications/channel.py
genesys_notifications/exceptions.py
genesys_notifications/states.py
genesys_notifications-1.3.dist-info/LICENSE
genesys_notifications-1.3.dist-info/METADATA
genesys_notifications-1.3.dist-info/WHEEL
genesys_notifications-1.3.dist-info/top_level.txt
genesys_notifications-1.3.dist-info/zip-safe
genesys_notifications-1.3.dist-info/RECORD
