Metadata-Version: 2.1
Name: genesys-notifications
Version: 1.3
Summary: genesys notifications client
Home-page: https://github.com/koodaamo/genesys-notifications
Author: Petri Savolainen
Author-email: petri@koodaamo.fi
License: GPLv2
Keywords: genesys,genesys cloud
Platform: UNKNOWN
Classifier: License :: OSI Approved :: GNU General Public License v2 (GPLv2)
Classifier: Programming Language :: Python :: 3
Classifier: Programming Language :: Python :: 3.10
License-File: LICENSE
Requires-Dist: websockets
Requires-Dist: ujson
